aws_embedded_metrics_helpers/__init__.py
aws_embedded_metrics_helpers/metrics.py
aws_embedded_metrics_helpers-0.1.5.dist-info/LICENSE
aws_embedded_metrics_helpers-0.1.5.dist-info/METADATA
aws_embedded_metrics_helpers-0.1.5.dist-info/WHEEL
aws_embedded_metrics_helpers-0.1.5.dist-info/top_level.txt
aws_embedded_metrics_helpers-0.1.5.dist-info/RECORD
