Metadata-Version: 2.1
Name: aws-embedded-metrics-helpers
Version: 0.1.5
Summary: Some helper decorators that use the aws-embedded-metrics to make publishing metrics from code a little bit easier
Author: Sabarna Chakravarty
Author-email: Sabarna Chakravarty <sabarnac@gmail.com>
Project-URL: Homepage, https://github.com/sabarnac/aws-embedded-metrics-python-helper
Project-URL: Bug Tracker, https://github.com/sabarnac/aws-embedded-metrics-python-helper/issues
Classifier: Programming Language :: Python :: 3
Classifier: License :: OSI Approved :: MIT License
Classifier: Operating System :: OS Independent
Requires-Python: >=3.8
License-File: LICENSE
Requires-Dist: aws-embedded-metrics
